{
  "lastUpdated": "2026-06-26T22:13:25-05:00",
  "timezone": "America/Chicago",
  "availability": [
    {
      "dayName": "Friday",
      "date": "06-26-2026",
      "availability": []
    },
    {
      "dayName": "Saturday",
      "date": "06-27-2026",
      "availability": []
    },
    {
      "dayName": "Sunday",
      "date": "06-28-2026",
      "availability": []
    },
    {
      "dayName": "Monday",
      "date": "06-29-2026",
      "availability": []
    },
    {
      "dayName": "Tuesday",
      "date": "06-30-2026",
      "availability": []
    },
    {
      "dayName": "Wednesday",
      "date": "07-01-2026",
      "availability": []
    },
    {
      "dayName": "Thursday",
      "date": "07-02-2026",
      "availability": []
    },
    {
      "dayName": "Friday",
      "date": "07-03-2026",
      "availability": []
    }
  ]
}